mc2skos/__init__.py
mc2skos/constants.py
mc2skos/element.py
mc2skos/jskos-context.json
mc2skos/mc2skos.py
mc2skos/reader.py
mc2skos/record.py
mc2skos/vocabularies.yml
mc2skos-0.9.0.dist-info/DESCRIPTION.rst
mc2skos-0.9.0.dist-info/METADATA
mc2skos-0.9.0.dist-info/RECORD
mc2skos-0.9.0.dist-info/WHEEL
mc2skos-0.9.0.dist-info/entry_points.txt
mc2skos-0.9.0.dist-info/metadata.json
mc2skos-0.9.0.dist-info/pbr.json
mc2skos-0.9.0.dist-info/top_level.txt
