Metadata-Version: 2.0
Name: mc2skos
Version: 0.9.0
Summary: Convert Marc21 Classification records in MARC/XML to SKOS/RDF 
Home-page: https://github.com/scriptotek/mc2skos
Author: Dan Michael O. Heggø
Author-email: danmichaelo@gmail.com
License: MIT
Keywords: marc rdf skos
Platform: UNKNOWN
Classifier: Programming Language :: Python
Classifier: Programming Language :: Python :: 2.7
Classifier: Programming Language :: Python :: 3.3
Classifier: Programming Language :: Python :: 3.4
Classifier: Programming Language :: Python :: 3.5
Classifier: Programming Language :: Python :: 3.6
Requires-Dist: rdflib
Requires-Dist: rdflib-jsonld
Requires-Dist: lxml
Requires-Dist: otsrdflib (<0.6.0,>=0.5.0)
Requires-Dist: iso-639
Requires-Dist: pyyaml
Requires-Dist: future
Requires-Dist: skosify (>=2.0.1)
